signum.cpython-310-i386-linux-gnu.so
csignum_fast-1.2.2.dist-info/WHEEL
csignum_fast-1.2.2.dist-info/top_level.txt
csignum_fast-1.2.2.dist-info/METADATA
csignum_fast-1.2.2.dist-info/RECORD
csignum_fast-1.2.2.dist-info/licenses/LICENSE
