Metadata-Version: 2.4
Name: csignum-fast
Version: 1.2.2
Summary: High-performance, versatile implementation of the universal 'sign' function for Python
Author-email: Alexandru Colesnicov <acolesnicov@gmx.com>
License: MIT
Project-URL: Homepage, https://github.com/acolesnicov/signum
Project-URL: Repository, https://github.com/acolesnicov/signum.git
Project-URL: Issues, https://github.com/acolesnicov/signum/issues
Project-URL: Changelog, https://github.com/acolesnicov/signum/blob/main/CHANGELOG.md
Keywords: Python,math,signum,sign,c-extension
Classifier: Development Status :: 5 - Production/Stable
Classifier: Intended Audience :: Developers
Classifier: Topic :: Software Development :: Libraries
Classifier: Programming Language :: C
Classifier: Programming Language :: Python :: 3.8
Classifier: Programming Language :: Python :: 3.9
Classifier: Programming Language :: Python :: 3.10
Classifier: Programming Language :: Python :: 3.11
Classifier: Programming Language :: Python :: 3.12
Classifier: Programming Language :: Python :: 3.13
Requires-Python: >=3.8
License-File: LICENSE
Dynamic: license-file
